py2mac/__init__.py
py2mac/application.py
py2mac/data_extraction/__init__.py
py2mac/data_extraction/main.py
py2mac/exceptions.py
py2mac/json_utils.py
py2mac/langchain_py2mac/__init__.py
py2mac/langchain_py2mac/tools.py
py2mac/ui.py
py2mac/utils.py
py2mac-0.1.2.dist-info/LICENSE
py2mac-0.1.2.dist-info/METADATA
py2mac-0.1.2.dist-info/WHEEL
py2mac-0.1.2.dist-info/RECORD
