Metadata-Version: 2.1
Name: py2mac
Version: 0.1.2
Summary: A Python Interface to macOS Accessibility API for UI Automation and AI Agents
Home-page: https://py2mac.wytrykus.dev/
License: Apache-2.0
Author: Rafal Wytrykus
Author-email: rafal@wytrykus.dev
Requires-Python: >=3.11,<4.0
Classifier: License :: OSI Approved :: Apache Software License
Classifier: Programming Language :: Python :: 3
Classifier: Programming Language :: Python :: 3.11
Classifier: Programming Language :: Python :: 3.12
Requires-Dist: attrs (>=23.2.0,<24.0.0)
Requires-Dist: pyobjc (>=10.2,<11.0)
Requires-Dist: pyobjc-framework-Accessibility (>=10.2,<11.0)
Requires-Dist: pyobjc-framework-ApplicationServices (>=10.2,<11.0)
Project-URL: Documentation, https://py2mac.wytrykus.dev/
Project-URL: Repository, https://github.com/rafalwytrykus/py2mac
